{
    "type": "FeatureCollection",
    "name": "Na'ama",
    "crs": { "type": "name", "properties": { "name": "urn:ogc:def:crs:EPSG::32236" } },
    "features": [
    { "type": "Feature", "properties": { "id": 5 }, "geometry": { "type": "Point", "coordinates": [ 35.46720131684097, 31.906449384296025 ] } }
]
}